LICENSE
MANIFEST.in
README.md
setup.py
bin/ptree
django_ptree/__init__.py
django_ptree/settings.py
django_ptree/urls.py
django_ptree/wsgi.py
django_ptree.egg-info/PKG-INFO
django_ptree.egg-info/SOURCES.txt
django_ptree.egg-info/dependency_links.txt
django_ptree.egg-info/requires.txt
django_ptree.egg-info/top_level.txt
ptree/__init__.py
ptree/admin.py
ptree/adminlib.py
ptree/app_template.zip
ptree/common.py
ptree/constants.py
ptree/fields.py
ptree/forms.py
ptree/forms_internal.py
ptree/project_template.zip
ptree/session.py
ptree/settings.py
ptree/urls.py
ptree/db/__init__.py
ptree/db/models.py
ptree/locale/de/LC_MESSAGES/django.mo
ptree/locale/de/LC_MESSAGES/django.po
ptree/management/__init__.py
ptree/management/commands/__init__.py
ptree/management/commands/create_sessions.py
ptree/management/commands/mturk_pay.py
ptree/management/commands/screenshots.py
ptree/management/commands/test.py
ptree/models/__init__.py
ptree/models/common.py
ptree/models/matches.py
ptree/models/participants.py
ptree/models/subsessions.py
ptree/models/treatments.py
ptree/sessionlib/__init__.py
ptree/sessionlib/models.py
ptree/static/jquery.animate-colors-min.js
ptree/static/jquery.animate-colors.js
ptree/static/jquery.min.js
ptree/static/pencil.png
ptree/static/robots.txt
ptree/static/bootstrap/css/bootstrap-theme.css
ptree/static/bootstrap/css/bootstrap-theme.min.css
ptree/static/bootstrap/css/bootstrap.css
ptree/static/bootstrap/css/bootstrap.min.css
ptree/static/bootstrap/fonts/glyphicons-halflings-regular.eot
ptree/static/bootstrap/fonts/glyphicons-halflings-regular.svg
ptree/static/bootstrap/fonts/glyphicons-halflings-regular.ttf
ptree/static/bootstrap/fonts/glyphicons-halflings-regular.woff
ptree/static/bootstrap/js/bootstrap.js
ptree/static/bootstrap/js/bootstrap.min.js
ptree/static/ptree/js/jquery.countdown.js
ptree/static/ptree/js/mturk_hit_page.js
ptree/templates/admin/_dashboard_app_template.html
ptree/templates/admin/ajax_actions.html
ptree/templates/admin/ajax_pagination.html
ptree/templates/admin/base_site.html
ptree/templates/admin/index.html
ptree/templates/admin/ptree_change_list.html
ptree/templates/admin/ptree_change_list_results.html
